{
    "name": "AWS PFM",
    "altnames": [
        "AWS",
        "Arctic Weather Satellite",
        "EPS-Sterna"
    ],
    "cospar": null,
    "norad": null,
    "icon": "AWS.gif",
    "downlinks": [
        {
            "name": "DDB/SMD",
            "description": "Combined Direct Data Broadcast and Stored Mission Data downlink",
            "note": "Future mission, SMD to be used during Svalbard contact only",
            "active": false,
            "frequency": 1707000000,
            "bandwidth": 3400000,
            "polarization": "RHC",
            "modulation": "QPSK",
            "symrate": 1785000,
            "broadcast": true
        }
    ]
}
